MANIFEST.in
README.rst
setup.py
aliyun_python_sdk_batchcompute.egg-info/PKG-INFO
aliyun_python_sdk_batchcompute.egg-info/SOURCES.txt
aliyun_python_sdk_batchcompute.egg-info/dependency_links.txt
aliyun_python_sdk_batchcompute.egg-info/requires.txt
aliyun_python_sdk_batchcompute.egg-info/top_level.txt
aliyunsdkbatchcompute/__init__.py
aliyunsdkbatchcompute/request/__init__.py
aliyunsdkbatchcompute/request/v20130111/DeleteImageRequest.py
aliyunsdkbatchcompute/request/v20130111/DeleteJobRequest.py
aliyunsdkbatchcompute/request/v20130111/DeleteSnapshotRequest.py
aliyunsdkbatchcompute/request/v20130111/GetImageRequest.py
aliyunsdkbatchcompute/request/v20130111/GetJobDescriptionRequest.py
aliyunsdkbatchcompute/request/v20130111/GetJobRequest.py
aliyunsdkbatchcompute/request/v20130111/GetSnapshotRequest.py
aliyunsdkbatchcompute/request/v20130111/GetTasksRequest.py
aliyunsdkbatchcompute/request/v20130111/ListImagesRequest.py
aliyunsdkbatchcompute/request/v20130111/ListJobsRequest.py
aliyunsdkbatchcompute/request/v20130111/ListSnapshotsRequest.py
aliyunsdkbatchcompute/request/v20130111/PostJobRequest.py
aliyunsdkbatchcompute/request/v20130111/PutJobRequest.py
aliyunsdkbatchcompute/request/v20130111/ReleaseJobRequest.py
aliyunsdkbatchcompute/request/v20130111/StartJobRequest.py
aliyunsdkbatchcompute/request/v20130111/StopJobRequest.py
aliyunsdkbatchcompute/request/v20130111/__init__.py
aliyunsdkbatchcompute/request/v20150630/DeleteJobRequest.py
aliyunsdkbatchcompute/request/v20150630/GetJobDescriptionRequest.py
aliyunsdkbatchcompute/request/v20150630/GetJobRequest.py
aliyunsdkbatchcompute/request/v20150630/GetTasksRequest.py
aliyunsdkbatchcompute/request/v20150630/ListImagesRequest.py
aliyunsdkbatchcompute/request/v20150630/ListJobsRequest.py
aliyunsdkbatchcompute/request/v20150630/ListSnapshotsRequest.py
aliyunsdkbatchcompute/request/v20150630/PostJobRequest.py
aliyunsdkbatchcompute/request/v20150630/PutJobRequest.py
aliyunsdkbatchcompute/request/v20150630/ReleaseJobRequest.py
aliyunsdkbatchcompute/request/v20150630/StartJobRequest.py
aliyunsdkbatchcompute/request/v20150630/StopJobRequest.py
aliyunsdkbatchcompute/request/v20150630/__init__.py